compilertools/__init__.py
compilertools/_config.py
compilertools/_config_build.py
compilertools/_core.py
compilertools/_src_files.py
compilertools/_utils.py
compilertools/build.py
compilertools/compilers/__init__.py
compilertools/compilers/_core.py
compilertools/compilers/gcc.py
compilertools/compilers/llvm.py
compilertools/compilers/msvc.py
compilertools/imports.py
compilertools/processors/__init__.py
compilertools/processors/_core.py
compilertools/processors/x86_32.py
compilertools/processors/x86_64.py
compilertools-1.1.5.dist-info/LICENSE
compilertools-1.1.5.dist-info/METADATA
compilertools-1.1.5.dist-info/WHEEL
compilertools-1.1.5.dist-info/RECORD
