Metadata-Version: 2.1
Name: compilertools
Version: 1.1.5
Summary: A library for helping optimizing Python extensions compilation.
Home-page: https://github.com/JGoutin/compilertools
License: BSD-2-Clause
Keywords: compiler,distutils,setuptools,build_ext,wheels,setup,build
Author: J.Goutin
Requires-Python: >=3.8,<4.0
Classifier: Development Status :: 5 - Production/Stable
Classifier: Intended Audience :: Developers
Classifier: License :: OSI Approved :: BSD License
Classifier: Programming Language :: Python
Classifier: Programming Language :: Python :: 3
Classifier: Programming Language :: Python :: 3.8
Classifier: Programming Language :: Python :: 3.9
Classifier: Programming Language :: Python :: 3.10
Classifier: Programming Language :: Python :: 3.11
Classifier: Programming Language :: Python :: 3
Classifier: Programming Language :: Python :: 3.10
Classifier: Programming Language :: Python :: 3.11
Classifier: Programming Language :: Python :: 3.8
Classifier: Programming Language :: Python :: 3.9
Classifier: Programming Language :: Python :: Implementation :: CPython
Classifier: Topic :: Software Development :: Build Tools
Project-URL: Documentation, https://jgoutin.github.io/compilertools/
Project-URL: Repository, https://github.com/JGoutin/compilertools
